ADPYNE/AutoDiff.py
ADPYNE/Dual.py
ADPYNE/Hessian.py
ADPYNE/__init__.py
ADPYNE/elemFunctions.py
ADPYNE/tests/AutoDiff_test.py
ADPYNE/tests/Dual_test.py
ADPYNE/tests/__init__.py
ADPYNE/tests/elemFunctions_Dual_test.py
ADPYNE/tests/elemFunctions_test.py
ADPYNE_207-0.1.4.dist-info/LICENSE
ADPYNE_207-0.1.4.dist-info/METADATA
ADPYNE_207-0.1.4.dist-info/WHEEL
ADPYNE_207-0.1.4.dist-info/top_level.txt
ADPYNE_207-0.1.4.dist-info/RECORD
