Metadata-Version: 2.1
Name: ADPYNE-207
Version: 0.1.4
Summary: Automatic Differentiation Package for Python
Home-page: https://github.com/PYNE-AD/cs207-FinalProject
Author: Group 12 - CS 207
Author-email: ptoroisaza@g.harvard.edu, nvanderklaauw@g.harvard.edu, emmali@college.harvard.edu, yaoweili@g.harvard.edu
License: UNKNOWN
Platform: UNKNOWN
Classifier: Programming Language :: Python :: 3
Classifier: License :: OSI Approved :: MIT License
Classifier: Operating System :: OS Independent
Requires-Python: >=3.6
Requires-Dist: numpy (>=1.16.4)
Requires-Dist: pytest (>=5.2.1)
